LICENSE
django_stomp_debug_callback/__init__.py
django_stomp_debug_callback/apps.py
django_stomp_debug_callback/urls.py
django_stomp_debug_callback/utils.py
django_stomp_debug_callback/views.py
django_stomp_debug_callback-2.0.0.dist-info/LICENSE
django_stomp_debug_callback-2.0.0.dist-info/METADATA
django_stomp_debug_callback-2.0.0.dist-info/WHEEL
django_stomp_debug_callback-2.0.0.dist-info/RECORD
