Metadata-Version: 2.1
Name: django-stomp-debug-callback
Version: 2.0.0
Summary: A simple view to help know what the callback is doing on django-stomp usage
Home-page: https://github.com/juntossomosmais/django-stomp-debug-callback
License: MIT
Keywords: django-stomp,stomp,django,development,django-debug
Author: Juntos Somos Mais
Author-email: labs@juntossomosmais.com.br
Requires-Python: >=3.10,<4.0
Classifier: License :: OSI Approved :: MIT License
Classifier: Programming Language :: Python :: 3
Classifier: Programming Language :: Python :: 3.10
Classifier: Programming Language :: Python :: 3.11
Requires-Dist: django
Requires-Dist: django-stomp (>=6.1.0,<7.0.0)
Project-URL: Repository, https://github.com/juntossomosmais/django-stomp-debug-callback
